Workbook

Sheet Resumen de exportación
B3: Este documento se ha exportado desde Numbers. Cada tabla se ha convertido en una hoja de cálculo de Excel. Los demás objetos de las hojas de Numbers se han colocado en distintas hojas de cálculo. Recuerda que el cálculo de fórmulas puede ser diferente en Excel.
B7: Nombre de hoja de Numbers | C7: Nombre de tabla de Numbers | D7: Nombre de hoja de cálculo de Excel
B9: TOTALES
C10: Tabla 1 | D10: TOTALES
B11: GENERAL Facturado
C12: Tabla 1 | D12: GENERAL Facturado
B13: GENERAL. Sin Facturar
C14: Tabla 1 | D14: GENERAL. Sin Facturar
B15: NES SA
C16: Tabla 1 | D16: NES SA
B17: ELECTRICIDAD
C18: Tabla 1 | D18: ELECTRICIDAD
B19: PLOMERIA
C20: Tabla 1 | D20: PLOMERIA
B21: ARQUITECTO
C22: Tabla 1 | D22: ARQUITECTO
B23: DRAP
C24: Tabla 1 | D24: DRAP
B25: ASCENSORES Y MONTA AUTOS
C26: Tabla 1 | D26: ASCENSORES Y MONTA AUTOS
B27: IMEPHO
C28: Tabla 1 | D28: IMEPHO

Sheet TOTALES
B1: $ | C1: U$S | F1: $ | G1: U$S
A2: SALDOS
A3: FACTURADO | B3: {='GENERAL Facturado'!J3} -> -7.7339499e+08 | C3: {='GENERAL Facturado'!K3} -> -2709504.5 | E3: DE MARZO 2018 A FEBRERO 2019
A4: SIN FACTURAR | B4: {='GENERAL. Sin Facturar'!J3} -> -1.8116874e+08 | C4: {='GENERAL. Sin Facturar'!K3} -> -1173504.1
E5: TOTAL BLANCO | F5: {=SUM('GENERAL Facturado'!G162:G252)} -> 6120284.9 | G5: {=SUM('GENERAL Facturado'!H162:H252)} -> 199553.39
A6: TOTAL | B6: {=SUM(B3:B4)} -> -9.5456373e+08 | C6: {=SUM(C3:C4)} -> -3883008.5 | E6: TOTAL NEGRO | F6: {=SUM('GENERAL. Sin Facturar'!G60:G114)} -> 4375640.8 | G6: {=SUM('GENERAL. Sin Facturar'!H60:H114)} -> 131993.64
E7: TOTAL | F7: {=SUM(F5:F6)} -> 10495926 | G7: {=SUM(G5:G6)} -> 331547.03
E11: DE MARZO 2019 A FEBRERO 2020 | K11: 0+
E13: TOTAL BLANCO | F13: {=SUM('GENERAL Facturado'!G253:G425)} -> 14863651 | G13: {=SUM('GENERAL Facturado'!H253:H425)} -> 234944.72
E14: TOTAL NEGRO | F14: {=SUM('GENERAL. Sin Facturar'!G115:G164)} -> 6930978.4 | G14: {=SUM('GENERAL. Sin Facturar'!H115:H164)} -> 126477.09
E15: TOTAL | F15: {=SUM(F13:F14)} -> 21794630 | G15: {=SUM(G13:G14)} -> 361421.81
E19: DE MARZO 2020 A FEBRERO 2021
E21: TOTAL BLANCO | F21: {=SUM('GENERAL Facturado'!G426:G575)} -> 17834502 | G21: {=SUM('GENERAL Facturado'!H426:H575)} -> 140941.87
E22: TOTAL NEGRO | F22: {=SUM('GENERAL. Sin Facturar'!G165:G234)} -> 22329412 | G22: {=SUM('GENERAL. Sin Facturar'!H165:H234)} -> 170729.74
E23: TOTAL | F23: {=SUM(F21:F22)} -> 40163914 | G23: {=SUM(G21:G22)} -> 311671.61
E27: DE MARZO 2023 A FEBRERO 2024
E29: TOTAL BLANCO | F29: {=SUM('GENERAL Facturado'!G722:G803)} -> 1.3726921e+08 | G29: {=SUM('GENERAL Facturado'!H722:H803)} -> 207721.16
E30: TOTAL NEGRO | F30: {=SUM('GENERAL. Sin Facturar'!G346:G372)} -> 50791284 | G30: {=SUM('GENERAL. Sin Facturar'!H346:H372)} -> 86022.39
E31: TOTAL | F31: {=SUM(F29:F30)} -> 1.8806049e+08 | G31: {=SUM(G29:G30)} -> 293743.55

Sheet GENERAL Facturado
E1: INGRESOS | G1: GASTOS | J1: SALDO
B2: COMPROBANTE | C2: PROVEEDOR | D2: . | E2: PESOS | F2: DOLARES | G2: PESOS | H2: DOLARES | I2: TIPO DE CAMBIO | J2: PESOS | K2: DOLARES
E3: {=SUM(E4:E1211)} -> 0 | F3: {=SUM(F4:F1211)} -> 0 | G3: {=SUM(G4:G1211)} -> 7.7339499e+08 | H3: {=SUM(H4:H1211)} -> 2709504.5 | J3: {=E3-G3} -> -7.7339499e+08 | K3: {=F3-H3} -> -2709504.5
A4: 40575 | D4: COMPRA LOTE | G4: {=H4*I4} -> 1722000 | H4: 420000 | I4: 4.1
A5: 40575 | D5: COMISION ESPATOLERO - COMPRA LOTE | G5: {=H5*I5} -> 28700 | H5: 7000 | I5: 4.1
A6: 40575 | D6: GTOS DE ESCRITURA - PEREZ LLANA | G6: {=H6*I6} -> 41000 | H6: 10000 | I6: 4.1
A7: 40585 | C7: ARBA | D7: IMPUESTO INMOBILIARIO - PAGO ANUAL 2011 | G7: 4660.4 | H7: {=G7/I7} -> 1122.988 | I7: 4.15
A8: 40620 | C8: OSSE | D8: PERIODO 01/2011 | G8: 31.96 | H8: {=G8/I8} -> 7.7012048 | I8: 4.15
A9: 40673 | C9: OSSE | D9: PERIODO 02/2011 | G9: 31.96 | H9: {=G9/I9} -> 7.4325581 | I9: 4.3
A10: 40732 | C10: OSSE | D10: PERIODO 03/2011 | G10: 63.92 | H10: {=G10/I10} -> 14.865116 | I10: 4.3
A11: 40857 | C11: OSSE | D11: PERIODO 05/2011 | G11: 63.92 | H11: {=G11/I11} -> 12.784 | I11: 5
A12: 40918 | C12: OSSE | D12: PERIODO 06/2011 | G12: 63.92 | H12: {=G12/I12} -> 13.316667 | I12: 4.8
A13: 40943 | C13: ARBA | D13: IMPUESTO INMOBILIARIO - PAGO ANUAL 2012 | G13: 18646.7 | H13: {=G13/I13} -> 3884.7292 | I13: {=I12} -> 4.8
A14: 40943 | C14: ARM | D14: IMPUESTO MUNICIPAL - PAGO ANUAL 2012 | G14: 14936.75 | H14: {=G14/I14} -> 3111.8229 | I14: {=I13} -> 4.8
A15: 40977 | C15: OSSE | D15: PERIODO 01/2012 | G15: 77.22 | H15: {=G15/I15} -> 16.0875 | I15: {=I14} -> 4.8
A16: 41039 | C16: OSSE | D16: PERIODO 02/2012 | G16: 77.22 | H16: {=G16/I16} -> 15.444 | I16: 5
A17: 41102 | C17: OSSE | D17: PERIODO 03/2012 | G17: 42.26 | H17: {=G17/I17} -> 6.9278689 | I17: 6.1
A18: 41160 | C18: OSSE | D18: PERIODO 04/2012 | G18: 42.26 | H18: {=G18/I18} -> 6.7079365 | I18: 6.3
A19: 41222 | C19: OSSE | D19: PERIODO 05/2012 | G19: 42.26 | H19: {=G19/I19} -> 6.7079365 | I19: {=I18} -> 6.3
A20: 41286 | C20: ARM | D20: IMPUESTO MUNICIPAL - PAGO ANUAL 2013 | G20: 18530.11 | H20: {=G20/I20} -> 2555.8772 | I20: 7.25
A21: 41351 | C21: OSSE | D21: PERIODO 01/2013 | G21: 69.36 | H21: {=G21/I21} -> 8.67 | I21: 8
A22: 41373 | C22: ARBA | D22: IMPUESTO INMOBILIARIO - PAGO ANUAL 2013 | G22: 19222.4 | H22: {=G22/I22} -> 2302.0838 | I22: 8.35
A23: 41404 | C23: OSSE | D23: PERIODO 02/2013 | G23: 69.36 | H23: {=G23/I23} -> 6.936 | I23: 10
A24: 41466 | C24: OSSE | D24: PERIODO 03/2013 | G24: 69.36 | H24: {=G24/I24} -> 8.4585366 | I24: 8.2
A25: 41527 | C25: OSSE | D25: PERIODOI 04/2013 | G25: 69.36 | H25: {=G25/I25} -> 7.5391304 | I25: 9.2
A26: 41547 | C26: ARM | D26: MUNICIPALIDAD | G26: 29868.81 | H26: {=G26/I26} -> 3144.0853 | I26: 9.5
A27: 41590 | C27: OSSE | D27: PERIODO 05/2013 | G27: 69.363 | H27: {=G27/I27} -> 7.0778571 | I27: 9.8
A28: 41600 | C28: OSSE | D28: INSTALACION AGUA Y KIT MEDICION | G28: 6165.5 | H28: {=G28/I28} -> 616.55 | I28: 10
A29: 41649 | C29: OSSE | D29: PERIODO 06/2013 | G29: 69.36 | H29: {=G29/I29} -> 6.4222222 | I29: 10.8
A30: 41666 | C30: ARM | D30: IMPUESTO MUNICIPAL - PAGO ANUAL 2014 | G30: 23762.37 | H30: {=G30/I30} -> 1980.1975 | I30: 12
A31: 41709 | C31: OSSE | D31: PERIODO 01/2014 | G31: 78.48 | H31: {=G31/I31} -> 7.2 | I31: 10.9
A32: 41718 | B32: 1331 | C32: AGRIMENSOR | D32: HONORARIOS | G32: 2500 | H32: {=G32/I32} -> 227.27273 | I32: 11
A33: 41743 | C33: ARBA | D33: IMPUESTO INMOBILIARIO - PAGO ANUAL 2014 | G33: 20234 | H33: {=G33/I33} -> 1964.466 | I33: 10.3
A34: 41767 | C34: OSSE | D34: PERIODO 02/2014 | G34: 78.48 | H34: {=G34/I34} -> 7.2984283 | I34: 10.753
A35: 41809 | C35: OSSE | D35: PERIODO 06/2014 | G35: 230.65 | H35: {=G35/I35} -> 18.600806 | I35: 12.4
A36: 41845 | C36: ARQUITECTO AGUERO MERCENARO | D36: HONORARIOS | G36: 150000 | H36: 15000 | I36: 10
A37: 41872 | C37: OSSE | D37: PERIODO 08/2014 | G37: 230.65 | H37: {=G37/I37} -> 16.475 | I37: 14
A38: 41914 | B38: 43425 | C38: IMEPHO | D38: HORMIGON - 392 M3 | G38: 449467.2 | H38: 32600 | I38: 13.8
A39: 41947 | B39: 44179 | C39: IMEPHO | D39: HORMIGON - 392.5 M3 | G39: 450040.5 | H39: 32600 | I39: 13.8
A40: 41950 | C40: OSSE | D40: PERIODO 10/2014 | G40: 232.88 | H40: {=G40/I40} -> 17.913846 | I40: 13
A41: 41954 | C41: OSSE | D41: PERIODO 09/2014 | G41: 243.34 | H41: {=G41/I41} -> 18.718462 | I41: {=I40} -> 13
A42: 41957 | C42: OSSE | D42: PERIODO 07/2014 | G42: 260.79 | H42: {=G42/I42} -> 19.46194 | I42: 13.4
A43: 41993 | C43: OSSE | D43: PERIODO 12/2014 | G43: 230.65 | H43: {=G43/I43} -> 17.742308 | I43: 13
A44: 42018 | C44: ARM | D44: TSH - PAGO ANUAL 2015 | G44: 31624.65 | H44: {=G44/I44} -> 2325.3419 | I44: 13.6
A45: 42030 | C45: OSSE | D45: PERIODO 01/2015 | G45: 840.31 | H45: {=G45/I45} -> 61.7875 | I45: {=I44} -> 13.6
A46: 42053 | C46: ARBA | D46: IMPUESTO INMOBILIARIO - PAGO ANUAL 2015 | G46: 26301.4 | H46: {=G46/I46} -> 2023.1846 | I46: 13
A47: 42073 | C47: OSSE | D47: PERIODO 02/2015 | G47: 1983.16 | H47: {=G47/I47} -> 154.93437 | I47: 12.8
A48: 42138 | C48: OSSE | D48: PERIODO 04/2015 | G48: 1472.48 | H48: {=G48/I48} -> 115.94331 | I48: 12.7
A49: 42138 | C49: OSSE | D49: PERIODO 03/2015 | G49: 1975.12 | H49: {=G49/I49} -> 155.52126 | I49: {=I48} -> 12.7
A50: 42138 | C50: OSSE | D50: DIFERENCIAS | G50: 294.53 | H50: {=G50/I50} -> 23.191339 | I50: {=I49} -> 12.7
A51: 42145 | C51: OSSE | D51: PERIODO 05/2015 | G51: 990.46 | H51: {=G51/I51} -> 77.988976 | I51: {=I50} -> 12.7
A52: 42173 | C52: OSSE | D52: PERIODO 06/2015 | G52: 333.16 | H52: {=G52/I52} -> 26.233071 | I52: 12.7
A53: 42205 | C53: OSSE | D53: PERIODO 07/2015 | G53: 333.16 | H53: {=G53/I53} -> 22.819178 | I53: 14.6
A54: 42238 | C54: OSSE | D54: PERIODO 08/2015 | G54: 333.16 | H54: {=G54/I54} -> 21.35641 | I54: 15.6
A55: 42241 | B55: 49634 | C55: IMEPHO | D55: COMPRA HORMIGON | G55: 599821.21 | H55: 37800 | I55: 15.87
A56: 42269 | C56: OSSE | D56: PERIODO 09/2015 | G56: 333.16 | H56: {=G56/I56} -> 20.8225 | I56: 16
A57: 42279 | C57: IMEPHO | D57: ACOPIO | G57: 1623051.8 | H57: 102078 | I57: 15.9
A58: 42298 | C58: OSSE | D58: PERIODO 10/2015 | G58: 333.16 | H58: {=G58/I58} -> 20.8225 | I58: {=I56} -> 16
A59: 42328 | C59: OSSE | D59: PERIODO 11/2015 | G59: 333.16 | H59: {=G59/I59} -> 22.210667 | I59: 15
A60: 42383 | C60: ARM | D60: IMPUESTO MUNICIPAL - CUOTA ANUAL 2016 | G60: 31658.95 | H60: {=G60/I60} -> 2261.3536 | I60: 14
A61: 42390 | C61: OSSE | D61: PERIODO 01/2016 | G61: 1387.52 | H61: {=G61/I61} -> 96.355556 | I61: 14.4
A62: 42416 | C62: ARBA | D62: IMPUESTO INMOBILIARIO - PAGO ANUAL 2016 | G62: 32462 | H62: {=G62/I62} -> 2164.1333 | I62: 15
A63: 42417 | C63: DERECHOS DE CONSTRUCCION | D63: DIFERENCIAS GTOS MUNICIPALES | G63: 5220 | H63: {=G63/I63} -> 341.17647 | I63: 15.3
A64: 42418 | C64: OSSE | D64: PERIODO 12/2015 | G64: 392.46 | H64: {=G64/I64} -> 25.567427 | I64: 15.35
A65: 42422 | C65: OSSE | D65: PERIODO 02/2016 | G65: 1875.8 | H65: {=G65/I65} -> 121.80519 | I65: 15.4
A66: 42441 | C66: OSSE | D66: DERECHOS CONSTRUCCION | G66: 516810 | H66: 35700 | I66: 14.5
A67: 42450 | C67: OSSE | D67: PERIODO 03/2016 | G67: 2119.94 | H67: {=G67/I67} -> 137.65844 | I67: 15.4
A68: 42485 | C68: EDEA | D68: PERIODO 02/2016 | G68: 923.02 | H68: {=G68/I68} -> 62.156229 | I68: 14.85
A69: 42539 | C69: OSSE | D69: PERIODO 06/2016 | G69: 850.43 | H69: {=G69/I69} -> 59.057639 | I69: 14.4
A70: 42550 | B70: 298 | C70: NES S.A. | D70: M.O. HORMIGON - CUOTA 1 | G70: 484600 | H70: 33145 | I70: {=G70/H70} -> 14.620606
A71: 42562 | C71: EDEA | D71: PERIODO 03/2016 - CTA. 02 | G71: 179.29 | H71: {=G71/I71} -> 11.952667 | I71: 15
A72: 42573 | C72: OSSE | D72: PERIODO 07/2016 | G72: 2892.48 | H72: {=G72/I72} -> 187.21553 | I72: 15.45
A73: 42584 | B73: 308 | C73: NES S.A. | D73: M.O. HORMIGON - CUOTA 2 | G73: 352950 | H73: 23220 | I73: {=G73/H73} -> 15.200258
A74: 42590 | C74: EDEA | D74: PERIODO 04/2016 - CTA. 01 | G74: 184.28 | H74: {=G74/I74} -> 12.005212 | I74: 15.35
A75: 42604 | C75: OSSE | D75: PERIODO 08/2016 | G75: 440.96 | H75: {=G75/I75} -> 28.5411 | I75: 15.45
A76: 42608 | C76: SEGURO FEDERACION PATRONAL | D76: DEL 25/08/2016 AL 25/08/2017 | G76: 29820.98 | H76: 2000 | I76: {=G76/H76} -> 14.91049
A77: 42611 | C77: CELTOP SRL | D77: MATERIALES | G77: 26676.29 | H77: 1780 | I77: 15
A78: 42615 | C78: ARM | D78: EXTRACCION 2 ARBOLES Y TRAMITES | G78: 18000 | H78: {=G78/I78} -> 1168.8312 | I78: 15.4
A79: 42615 | B79: 321 | C79: NES S.A. | D79: M.O. HORMIGON - CUOTA 3 | G79: 418775.17 | H79: 27550 | I79: {=G79/H79} -> 15.200551
A80: 42618 | B80: 322 | C80: NES S.A. | D80: M.O. HORMIGON - CUOTA 4 | G80: 418775.17 | H80: 27550 | I80: {=G80/H80} -> 15.200551
A81: 42633 | C81: EDEA | D81: PERIODO 04/2016 - CTA. 02 | G81: 274.25 | H81: {=G81/I81} -> 17.412698 | I81: 15.75
A82: 42634 | C82: OSSE | D82: PERIODO 09/2016 | G82: 448.48 | H82: {=G82/I82} -> 28.565605 | I82: 15.7
A83: 42649 | C83: EDEA | D83: PERIODO 05/2016 - CTA . 01 | G83: 285.04 | H83: {=G83/I83} -> 18.271795 | I83: 15.6
A84: 42662 | C84: OSSE | D84: PERIODO 10/2016 | G84: 487.19 | H84: {=G84/I84} -> 31.130351 | I84: 15.65
A85: 42681 | C85: EDEA | D85: PERIODO 05/2016 - CTA. 02 | G85: 287.16 | H85: {=G85/I85} -> 18.526452 | I85: 15.5
A86: 42681 | B86: 348 | C86: NES S.A. | D86: M.O. HORMIGON - CUOTA 5 | G86: 459940.77 | H86: 30660 | I86: {=G86/H86} -> 15.00133
A87: 42681 | B87: 349 | C87: NES S.A. | D87: M.O. HORMIGON - CUOTA 6 | G87: 459940.77 | H87: 30660 | I87: {=G87/H87} -> 15.00133
A88: 42688 | B88: 691 | C88: CAPARELLI | D88: TERGOPORLES P/LOZAS | G88: 285875 | H88: 19058 | I88: {=G88/H88} -> 15.000262
A89: 42695 | C89: OSSE | D89: PERIODO 11/2016 | G89: 494.71 | H89: {=G89/I89} -> 31.310759 | I89: 15.8
A90: 42717 | C90: EDEA | D90: PERIODO 06/2016 - CTA. 01 | G90: 607.36 | H90: {=G90/I90} -> 37.034146 | I90: 16.4
A91: 42725 | C91: OSSE | D91: PERIODO 12/2016 | G91: 517.27 | H91: {=G91/I91} -> 31.160843 | I91: 16.6
A92: 42739 | B92: 366 | C92: NES S.A. | D92: M.O. HORMIGON - CUOTA 7 | G92: 459940.77 | H92: 28750 | I92: {=G92/H92} -> 15.99794
A93: 42747 | C93: EDEA | D93: PERIODO 06/2016 - CTA. 02 | G93: 609.76 | H93: {=G93/I93} -> 36.295238 | I93: 16.8
A94: 42754 | C94: ARM | D94: IMPUESTO MUNICIPAL - PAGO ANUAL 2017 | G94: 35432.81 | H94: {=G94/I94} -> 2096.616 | I94: 16.9
A95: 42758 | C95: OSSE | D95: PERIODO 01/2017 | G95: 482.79 | H95: {=G95/I95} -> 28.567456 | I95: {=I94} -> 16.9
A96: 42772 | C96: EDEA | D96: PERIODO 01/2017 - CTA. 01 | G96: 415.65 | H96: {=G96/I96} -> 25.190909 | I96: 16.5
A97: 42773 | B97: 373 | C97: NES S.A. | D97: M.O. HORMIGON - CUOTA 8 | G97: 477142.54 | H97: 29800 | I97: {=G97/H97} -> 16.011495
A98: 42782 | C98: ARBA | D98: IMPUESTO INMOBILIARIO - PAGO ANUAL 2017 | G98: 44799.2 | H98: {=G98/I98} -> 2748.4172 | I98: 16.3
A99: 42788 | C99: OSSE | D99: PERIODO 02/2017 | G99: 517.27 | H99: {=G99/I99} -> 31.540854 | I99: 16.4
A100: 42796 | B100: 379 | C100: NES S.A. | D100: M.O. HORMIGON - CUOTA 9 | G100: 477142.54 | H100: 30200 | I100: {=G100/H100} -> 15.799422
...

Sheet GENERAL. Sin Facturar
E1: INGRESOS | G1: GASTOS | J1: SALDO
A2: FECHA | B2: COMPROBANTE | C2: PROVEEDOR | D2: CONCEPTO | E2: PESOS | F2: DOLARES | G2: PESOS | H2: DOLARES | I2: TIPO DE CAMBIO | J2: PESOS | K2: DOLARES
E3: {=SUM(E4:E985)} -> 67402037 | F3: {=SUM(F4:F985)} -> 145084.85 | G3: {=SUM(G4:G1078)} -> 2.4857077e+08 | H3: {=SUM(H4:H1078)} -> 1318588.9 | J3: {=E3-G3} -> -1.8116874e+08 | K3: {=F3-H3} -> -1173504.1
A4: 2010-2011 | C4: ALQUILER | D4: TEMPORADA 2010 - 2011 | E4: 44000 | F4: 10700 | I4: {=E4/F4} -> 4.1121495
A5: 2011-2012 | C5: ALQUILER | D5: TEMPORADA 2011 - 2012 | E5: 57200 | F5: 13000 | I5: {=E5/F5} -> 4.4
A6: 2012-2013 | C6: ALQUILER | D6: TEMPORADA 2012 - 2013 | E6: 70000 | F6: 14000 | I6: {=E6/F6} -> 5
A7: 41296 | C7: HIERROMETAL | D7: HIERRO DE 10 Y 12MM. | G7: 150008.28 | H7: 19946 | I7: 7.5
A8: 41296 | C8: HIERROMETAL | D8: HIERRO DE 6,8 Y 10MM. | G8: 150028.5 | H8: 19946 | I8: 7.5
A9: 41470 | C9: ARQUITECTO AGUERO MARCENARO | D9: HONORARIOS | G9: 35000 | H9: 5000 | I9: 7
A10: 41508 | C10: ARQUITECTO AGUERO MARCENARO | D10: HONORARIOS | G10: 36000 | H10: 5000 | I10: 7
A11: SEP - 2013 | C11: ARQUITECTO AGUERO MARCENARO | D11: HONORARIOS | G11: 220000 | H11: 30000 | I11: 7.33
A12: 2013-2014 | C12: ALQUILER | D12: TEMPORADA 2013 - 2014 | E12: 105000 | F12: 9200 | I12: {=E12/F12} -> 11.413043
A13: 42104 | C13: OSSE | D13: COBRO OBRAS SANITARIAS - DICIEMBRE 2014, ENERO, FEBRERO Y MARZO 2015 | E13: 3900 | F13: {=E13/I13} -> 314.51613 | I13: 12.4
A14: 41740 | C14: ARQUITECTO AGUERO MARCENARO | D14: HONORARIOS ?? | G14: 11000 | H14: {=G14/I14} -> 1057.6923 | I14: 10.4
A15: 41921 | B15: FACTURA 44179 | C15: IMEPHO | D15: HIERROS DE 12,16,20 Y 25 MM. | G15: 322719.6 | H15: 23730 | I15: 13.6
A16: 2014 - 2015 | C16: ALQUILER | D16: TEMPORADA 2014 - 2015 | E16: 144000 | F16: 12000 | I16: {=E16/F16} -> 12
A17: 42172 | C17: OSSE | D17: COBRO OBRAS SANITARIAS | E17: 1600 | F17: {=(E17/I17)} -> 123.07692 | I17: 13
A18: 42237 | C18: PALOMO | D18: TRANSPORTE TIERRA | G18: 7300 | H18: {=G18/I18} -> 467.94872 | I18: 15.6
A19: 2015 - 2016 | C19: ALQUILER | D19: TEMPORADA 2015 - 2016 | E19: 200000 | F19: 12900 | I19: {=E19/F19} -> 15.503876
A20: 42417 | C20: ARQUITECTO AGUERO MARCENARO | D20: HONORARIOS | G20: 200000 | H20: 15000 | I20: 13.3
A21: 42441 | C21: NES S.A. | D21: A CTA. PRINCIPIO DE EFECUCION | G21: 400000 | H21: 25560 | I21: 15.65
A22: 42441 | C22: NES S.A. | D22: A CTA. CLAUSULA ADICIONAL | G22: 782500 | H22: {=G22/I22} -> 50000 | I22: {=I21} -> 15.65
A23: 42459 | C23: NES S.A. | D23: PAGO | G23: 767500 | H23: 50000 | I23: 15.4
A24: 42530 | C24: NES S.A. | D24: PAGO | G24: 225000 | H24: 15000 | I24: 15
A25: 42530 | C25: NES S.A. | D25: PAGO | G25: 25000 | H25: {=G25/I25} -> 1666.6667 | I25: 15
A26: 42172 | C26: OSSE | D26: COBRO OBRAS SANITARIAS | E26: 1600 | F26: {=E26/I26} -> 123.07692 | I26: 13
A27: 42584 | C27: ARQUITECTO AGUERO MARCENARO | D27: CUOTA 01 - AÑO 2016 | G27: 148000 | H27: 10000 | I27: {=G27/H27} -> 14.8
A28: 42618 | C28: ELECTRICIDAD | D28: DIEGO - M.O. LOZAS | G28: 54000 | H28: 3220 | I28: {=G28/H28} -> 16.770186
A29: 42663 | C29: ELECTRICIDAD | D29: CASA BLANCO MATERIALES | G29: 60000 | H29: 3636 | I29: {=G29/H29} -> 16.50165
A30: 42787 | D30: BOMBA DE AGUA | G30: 4000 | H30: {=G30/I30} -> 243.90244 | I30: 16.4
A31: 42789 | C31: ARQUITECTO AGUERO MARCENARO | D31: CUOTA 02 - AÑO 2017 | G31: 160000 | H31: 10000 | I31: 16
A32: 42812 | C32: CORRALON | D32: COMPRA | G32: 14591 | H32: 972 | I32: {=G32/H32} -> 15.011317
A33: 42858 | C33: HIERROMETAL | D33: DIFERENCIAS | G33: 24000 | H33: 1500 | I33: {=G33/H33} -> 16
A34: 42861 | C34: PINTURA - VICTOR | D34: PAGO | G34: 6000 | H34: {=G34/I34} -> 375 | I34: 16
A35: 42886 | D35: CONFECCION RENDEL | G35: 9000 | H35: {=G35/I35} -> 548.78049 | I35: 16.4
A36: 42928 | C36: ELECTRICIDAD | D36: CASA BLANCO MATERIALES | G36: 1200 | H36: 70 | I36: {=G36/H36} -> 17.142857
A37: 42950 | D37: CAMBIO TRIFACICA | G37: 3140 | H37: {=G37/I37} -> 172.52747 | I37: 18.2
A38: 42958 | C38: NES S.A. | D38: JUAN - 1°ETAPA - CUOTA 1 | G38: 200000 | H38: 10800 | I38: {=G38/H38} -> 18.518519
A39: 42962 | D39: LAMPARITAS | G39: 230 | H39: {=G39/I39} -> 12.672176 | I39: 18.15
A40: 42963 | D40: PINTURA MERCENARO | G40: 1300 | H40: {=G40/I40} -> 71.038251 | I40: 18.3
A41: 42983 | C41: ASCENSORES | D41: IMPERM. HUECO ASCENSORES Y MONTA AUTOS | G41: 18000 | H41: 1000 | I41: 18
A42: 42997 | C42: NES S.A. | D42: JUAN - 1°ETAPA - CUOTA 2 | G42: 200000 | H42: 11050 | I42: {=G42/H42} -> 18.099548
A43: 43005 | D43: CARNE | G43: 2220 | H43: {=G43/I43} -> 123.33333 | I43: 18
A44: 43018 | C44: NES S.A. | D44: JUAN - 1°ETAPA - CUOTA 3 | G44: 200000 | H44: 11436 | I44: {=G44/H44} -> 17.488632
A45: 43027 | C45: NES S.A. | D45: M.O. HORMIGON - ADICIONALES | G45: 532000 | H45: 31457 | I45: {=G45/H45} -> 16.911975
A46: 43041 | D46: CARNE | G46: 5387 | H46: {=G46/I46} -> 299.27778 | I46: 18
A47: 43042 | C47: ASCENSORES | D47: COMPRA MONTA AUTOS ULTRA | G47: 200000 | H47: 11100 | I47: {=G47/H47} -> 18.018018
A48: 43049 | C48: NES S.A. | D48: JUAN- 1°ETAPA - CUOTA 4 | G48: 200000 | H48: 11200 | I48: {=G48/H48} -> 17.857143
A49: 43075 | C49: STARKLOFF | D49: METALIZADOS MONTA AUTOS | G49: 132000 | H49: 7000 | I49: {=G49/H49} -> 18.857143 | J49: ORIGINAL 156200 (u$s8335) 24200 EN B Y 132000 EN N
A50: 43079 | C50: NES S.A. | D50: JUAN - 1°ETAPA - CUOTA 5 | G50: 200000 | H50: 11200 | I50: {=G50/H50} -> 17.857143
A51: 43081 | D51: CARNE | G51: 1911 | H51: {=G51/I51} -> 106.16667 | I51: 18
A52: 43084 | D52: COLOCACION CARTEL | G52: 7200 | H52: {=G52/I52} -> 400 | I52: 18
A53: 43108 | D53: CARNE | G53: 2200 | H53: {=G53/I53} -> 112.2449 | I53: 19.6
A54: 43122 | D54: PAGO A CTA. IMPERMEABILIZACION | G54: 14000 | H54: {=G54/I54} -> 703.51759 | I54: 19.9
A55: 43134 | C55: LANDA | D55: PLASTICOR | G55: 7714 | H55: {=G55/I55} -> 385.7 | I55: 20
A56: 43134 | C56: ZUBILLAGA | D56: TACOS MADERA | G56: 7392 | H56: {=G56/I56} -> 369.6 | I56: {=I55} -> 20
A57: FEB - 2018 | C57: ARQUITECTO AGUERO MARCENARO | D57: CUOTA 03 - AÑO 2018 | G57: 100000 | H57: 5000 | I57: 20 | J57: 50% Y 50% ($200000(u$s10000) ORIGINALES)
A58: 43137 | D58: CARNE | G58: 1500 | H58: {=G58/I58} -> 75.376884 | I58: 19.9
A59: 43158 | C59: MARIÑO | D59: IMPERMEABILIZACION | G59: 55000 | H59: {=G59/I59} -> 2763.8191 | I59: 19.9
A60: 43181 | C60: NES S.A. | D60: 2°ETAPA - A CTA. ANTICIPO | G60: 200000 | H60: 9615 | I60: {=G60/H60} -> 20.800832
A61: 43181 | C61: CORRALON | D61: JUAN B JUSTO - COMPRA | G61: 12321 | H61: 592 | I61: {=G61/H61} -> 20.8125
A62: 43182 | C62: PINTURA - VICTOR | D62: TRABAJO DE PINTURA | G62: 18500 | H62: 907 | I62: {=G62/H62} -> 20.396913
A63: 43199 | C63: NES S.A. | D63: 2°ETAPA - A CTA. ANTICIPO | G63: 140000 | H63: 6760 | I63: {=G63/H63} -> 20.710059
A64: 43206 | D64: REPUESTO BOMBA DE AGUA | G64: 550 | H64: {=G64/I64} -> 26.570048 | I64: 20.7
A65: 43215 | C65: NES S.A. | D65: SALDO ANTICIPO | G65: 60000 | H65: 2927 | I65: {=G65/H65} -> 20.498804
A66: 43215 | C66: NES S.A. | D66: 2°ETAPA: CUOTA 1 | G66: 150000 | H66: 7073 | I66: {=G66/H66} -> 21.207408
A67: 43231 | C67: PLOMERIA | D67: DESAGUES | G67: 3668 | H67: 158 | I67: {=G67/H67} -> 23.21519
A68: 43238 | C68: NES S.A. | D68: 2°ETAPA: CUOTA 2 | G68: 150000 | H68: 6000 | I68: {=G68/H68} -> 25
A69: 43266 | D69: CARNE | G69: 2090 | H69: {=G69/I69} -> 74.642857 | I69: 28
A70: 43270 | C70: PLOMERIA | D70: TRABAJO DE CAÑERIAS EN PILETAS | G70: 20000 | H70: {=G70/I70} -> 714.28571 | I70: {=I69} -> 28
A71: 43298 | D71: COLOCACION BANDEJA NUEVA - MANO DE OBRA | G71: 45000 | H71: 1600 | I71: {=G71/H71} -> 28.125
A72: 43298 | C72: NES S.A. | D72: 2°ETAPA: CUOTA 4 | G72: 150000 | H72: 5270 | I72: 28.5
A73: 43312 | C73: ELECTRICIDAD | D73: DIEGO - ELECTRICISTA | G73: 31000 | H73: 1100 | I73: {=I72} -> 28.5
A74: 43326 | C74: SANITARIOS SANCHEZ | D74: CAÑOS, CODOS, CANILLA, GRAMPA, ETC. | G74: 940 | H74: 32 | I74: {=G74/H74} -> 29.375
A75: 43327 | C75: NES S.A. | D75: 2°ETAPA: CUOTA 5 | G75: 150000 | H75: {=G75/I75} -> 5084.7458 | I75: 29.5
A76: 43335 | D76: PRECINTOS 200*4,7 x 100U | G76: 810 | H76: 27 | I76: {=G76/H76} -> 30
A77: 43708 | C77: ELECTRICIDAD | D77: DIEGO ELECTRICISTA - MANO DE OBRA | G77: 40000 | H77: 1100 | I77: {=G77/H77} -> 36.363636
A78: 43348 | C78: PINTURA - VICTOR | D78: MANO DE OBRA 1º Y 2º SUBSUELO | G78: 76458 | H78: 1920 | I78: {=G78/H78} -> 39.821875
A79: 43348 | C79: PINTURA - VICTOR | D79: MANO DE OBRA MONTAUTOS | G79: 30000 | H79: 769 | I79: {=G79/H79} -> 39.011704
A80: 43733 | C80: ELECTRICIDAD | D80: DIEGO ELECTRICISTA - MANO DE OBRA | G80: 40000 | H80: 1000 | I80: {=G80/H80} -> 40
A81: 43369 | C81: ARQUITECTO AGUERO MARCENARO | D81: IMPERBEALIZACION DE LOSA | G81: 221400 | H81: 5535 | I81: {=G81/H81} -> 40 | M81: U$S 468044.59 OK al 26/09/18
A82: 43382 | C82: NES S.A. | D82: 2°ETAPA: CUOTA 7 | G82: 150000 | H82: 3850 | I82: {=G82/H82} -> 38.961039
A83: 43382 | C83: DERECHOS DE CONSTRUCCION | D83: TRAMITES MUNICIPALES | G83: 4800 | H83: 126 | I83: {=G83/H83} -> 38.095238
A84: 43391 | C84: ELECTRICIDAD | D84: DIEGO - ELECTRICISTA (MATERIALES) | G84: 1800 | H84: 49 | I84: {=G84/H84} -> 36.734694
A85: 43397 | C85: VARIOS | D85: SACAR CHIMENEA (SALINAS) | G85: 16000 | H85: 432 | I85: {=G85/H85} -> 37.037037
A86: 43402 | C86: SEGURIDAD OBRA | D86: MES DE NOVIEMBRE | G86: 4800 | H86: {=G86/I86} -> 129.72973 | I86: 37 | L86: 7528178.4 | M86: 470118.24
A87: 43411 | C87: NES S.A. | D87: 2°ETAPA: CUOTA 7 - SALDO | G87: 7500 | H87: 203 | I87: {=I86} -> 37
A88: 43411 | C88: NES S.A. | D88: 2ºETAPA: CUOTA 8 | G88: 163800 | H88: {=G88/I88} -> 4427.027 | I88: {=I87} -> 37
A89: 43413 | C89: CARNE | G89: 2922 | H89: {=G89/I89} -> 81.166667 | I89: 36
A90: 43420 | C90: ELECTRICIDAD | D90: 20 LAMPARAS LED | G90: 1400 | H90: 38 | I90: {=G90/H90} -> 36.842105
A91: 43791 | C91: ELECTRICIDAD | D91: DIEGO ELECTRICISTA - MANO DE OBRA | G91: 70000 | H91: 1945 | I91: {=G91/H91} -> 35.989717
A92: 43427 | C92: VARIOS | D92: MIGUEL DURLOX - CEMENTO DIVISION COCHERA/EDIFICIO | G92: 60000 | H92: {=857*2} -> 1714 | I92: {=G92/H92} -> 35.005834
A93: 43439 | C93: SALINAS | D93: REVOCAR PARED CHIMENEA | G93: 13000 | H93: {=G93/I93} -> 351 | I93: {=I85} -> 37.037037
A94: 43440 | C94: VARIOS | D94: COLOCACION MEMBRANA EN PB, PATIOS Y BALCONES (MARIÑO) | G94: 55000 | H94: {=G94/I94} -> 1506.8493 | I94: 36.5
A95: 13/12/2018 | C95: SEGURIDAD OBRA | D95: DICIEMBRE DE 2018 | G95: 4000 | H95: {=G95/I95} -> 109.58904 | I95: {=I94} -> 36.5
A96: 43447 | C96: PLOMERIA | D96: DESAGUES DE 2 PATIOS, 2 BALCONES Y CANILLA COCHERA | G96: 7000 | H96: 190 | I96: {=I95} -> 36.5
A97: 43813 | C97: ELECTRICIDAD | D97: DIEGO ELECTRICISTA - MANO DE OBRA | G97: 20000 | H97: 540 | I97: {=G97/H97} -> 37.037037
A98: 43452 | C98: CASA BLANCO | D98: MATERIALES Y LUCES | G98: 24340 | H98: 640 | I98: {=I96} -> 36.5
A99: 43452 | C99: NES S.A. | D99: 2ºETAPA: CUOTA Nº9 (SALDO) | G99: 68714 | H99: 1808 | I99: {=I98} -> 36.5
A100: 43457 | C100: SALINAS | D100: PINTURA PATIO CONTRAFRENTE EN MEDIANERA | G100: 50000 | H100: 1350 | I100: {=I99} -> 36.5
...

Sheet NES SA
C2: NES S.A.: HORMIGON
A4: FECHA | B4: COMPROBANTE | C4: PROVEEDOR | D4: CONCEPTO | E4: PESOS | F4: DOLARES | G4: TIPO DE CAMBIO
A5: 42441 | C5: NES S.A. | D5: A CTA. PRINCIPIO DE EFECUCION | E5: 400000 | F5: 25560 | G5: 15.65
A6: 42441 | C6: NES S.A. | D6: A CTA. CLAUSULA ADICIONAL | E6: 782500 | F6: {=E6/G6} -> 50000 | G6: {=G5} -> 15.65
A7: 42459 | C7: NES S.A. | D7: PAGO | E7: 767500 | F7: 50000 | G7: {=G6} -> 15.65
A8: 42530 | C8: NES S.A. | D8: PAGO | E8: 225000 | F8: 15000 | G8: 15
A9: 42530 | C9: NES S.A. | D9: PAGO | E9: 25000 | F9: {=E9/G9} -> 1666.6667 | G9: 15
A10: 42550 | C10: NES S.A. | D10: M.O. HORMIGON - CUOTA 1 | E10: 484600 | F10: 33145 | G10: {=E10/F10} -> 14.620606
A11: 42584 | C11: NES S.A. | D11: M.O. HORMIGON - CUOTA 2 | E11: 352950 | F11: 23220 | G11: {=E11/F11} -> 15.200258
A12: 42615 | C12: NES S.A. | D12: M.O. HORMIGON - CUOTA 3 | E12: 418775.17 | F12: 27550 | G12: {=E12/F12} -> 15.200551
A13: 42618 | C13: NES S.A. | D13: M.O. HORMIGON - CUOTA 4 | E13: 418775.17 | F13: 27550 | G13: {=E13/F13} -> 15.200551
A14: 42681 | C14: NES S.A. | D14: M.O. HORMIGON - CUOTA 5 | E14: 459940.77 | F14: 30660 | G14: {=E14/F14} -> 15.00133
A15: 42681 | C15: NES S.A. | D15: M.O. HORMIGON - CUOTA 6 | E15: 459940.77 | F15: 30660 | G15: {=E15/F15} -> 15.00133
A16: 42739 | C16: NES S.A. | D16: M.O. HORMIGON - CUOTA 7 | E16: 459940.77 | F16: 28750 | G16: {=E16/F16} -> 15.99794
A17: 42773 | C17: NES S.A. | D17: M.O. HORMIGON - CUOTA 8 | E17: 477142.54 | F17: 29800 | G17: {=E17/F17} -> 16.011495
A18: 42796 | C18: NES S.A. | D18: M.O. HORMIGON - CUOTA 9 | E18: 477142.54 | F18: 30200 | G18: {=E18/F18} -> 15.799422
A19: 42842 | C19: NES S.A. | D19: M.O. HORMIGON - CUOTA 10 | E19: 477142.54 | F19: 29272 | G19: {=E19/F19} -> 16.300305
A20: 42864 | C20: NES S.A. | D20: M.O. HORMIGON - CUOTA 11 | E20: 190857.05 | F20: 11227 | G20: {=E20/F20} -> 16.999826
A21: 42891 | C21: NES S.A. | D21: M.O. HORMIGON - CUOTA 12 | E21: 211851.32 | F21: 13000 | G21: {=E21/F21} -> 16.296255
... A25: 43027 | C25: NES S.A. | D25: M.O. HORMIGON - ADICIONALES | E25: 532000 | F25: 31457 | G25: {=E25/F25} -> 16.911975
B27: TOTAL | E27: {=SUM(E5:E25)} -> 8298982.9 | F27: {=SUM(F5:F25)} -> 526427.67
C30: NES S.A.: JUAN 1°ETAPA: SUBSUELOS, PLANTA BAJA Y CONTRAFRENTE
A32: FECHA | B32: COMPROBANTE | C32: PROVEEDOR | D32: CONCEPTO | E32: PESOS | F32: DOLARES | G32: TIPO DE CAMBIO
A33: 42898 | C33: NES S.A. | D33: JUAN - 1°ETAPA - ANTICIPO | E33: 605750 | F33: 37000 | G33: {=E33/F33} -> 16.371622
A34: 42958 | C34: NES S.A. | D34: JUAN - 1°ETAPA - CUOTA 1 | E34: 200000 | F34: 10800 | G34: {=E34/F34} -> 18.518519
A35: 42989 | C35: NES S.A. | D35: JUAN - 1°ETAPA - CUOTA 2 | E35: 200000 | F35: 11050 | G35: {=E35/F35} -> 18.099548
A36: 43019 | C36: NES S.A. | D36: JUAN - 1°ETAPA - CUOTA 3 | E36: 200000 | F36: 11436 | G36: {=E36/F36} -> 17.488632
A37: 43049 | C37: NES S.A. | D37: JUAN- 1°ETAPA - CUOTA 4 | E37: 200000 | F37: 11200 | G37: {=E37/F37} -> 17.857143
A38: 43079 | C38: NES S.A. | D38: JUAN - 1°ETAPA - CUOTA 5 | E38: 200000 | F38: 11200 | G38: {=E38/F38} -> 17.857143
B40: TOTAL | E40: {=SUM(E33:E38)} -> 1605750 | F40: {=SUM(F33:F38)} -> 92686
C43: NES S.A.: JUAN 2°ETAPA: CIERRE PAREDES
A45: FECHA | B45: COMPROBANTE | C45: PROVEEDOR | D45: CONCEPTO | E45: PESOS | F45: DOLARES | G45: TIPO DE CAMBIO
A46: 43060 | C46: NES S.A. | D46: 2°ETAPA - A CTA. ANTICIPO | E46: 363450 | F46: 20600 | G46: {=E46/F46} -> 17.643204
A47: 43075 | C47: NES S.A. | D47: 2°ETAPA - A CTA. ANTICIPO | E47: 605750 | F47: 34126 | G47: {=E47/F47} -> 17.750396
A48: 43120 | C48: NES S.A. | D48: 2°ETAPA - A CTA. ANTICIPO | E48: 848050 | F48: 43700 | G48: {=E48/F48} -> 19.406178
A49: 43150 | C49: NES S.A. | D49: 2°ETAPA - A CTA. ANTICIPO | E49: 605750 | F49: 29850 | G49: {=E49/F49} -> 20.293132
A50: 43181 | C50: NES S.A. | D50: 2°ETAPA - A CTA. ANTICIPO | E50: 200000 | F50: 9615 | G50: {=E50/F50} -> 20.800832
A51: 43199 | C51: NES S.A. | D51: 2°ETAPA - A CTA. ANTICIPO | E51: 140000 | F51: 6760 | G51: {=E51/F51} -> 20.710059
A52: 43215 | C52: NES S.A. | D52: SALDO ANTICIPO | E52: 60000 | F52: 2927 | G52: {=E52/F52} -> 20.498804
A53: 43215 | C53: NES S.A. | D53: 2°ETAPA: CUOTA 1 | E53: 150000 | F53: 7073 | G53: {=E53/F53} -> 21.207408
A54: 43238 | C54: NES S.A. | D54: 2°ETAPA: CUOTA 2 | E54: 150000 | F54: 6000 | G54: {=E54/F54} -> 25
A55: 43264 | C55: NES S.A. | D55: 2°ETAPA: CUOTA 3 | E55: 181500 | F55: 6260 | G55: 29
A56: 43298 | C56: NES S.A. | D56: 2°ETAPA: CUOTA 4 | E56: 150000 | F56: 5270 | G56: 28.5
A57: 43327 | C57: NES S.A. | D57: 2°ETAPA: CUOTA 5 | E57: 150000 | F57: {=E57/G57} -> 5084.7458 | G57: 29.5
A58: 43357 | B58: 508 | C58: NES S.A. | D58: 2º ETAPA: CUOTA 6 | E58: 190575 | F58: {=E58/G58} -> 4764.375 | G58: 40
A59: 43382 | C59: NES S.A. | D59: 2°ETAPA: CUOTA 7 | E59: 150000 | F59: 3850 | G59: {=E59/F59} -> 38.961039
A60: 43411 | C60: NES S.A. | D60: 2ºETAPA: CUOTA 8 | E60: 163800 | F60: 4427.027 | G60: 37
A61: 43439 | B61: 520 | C61: NES S.A. | D61: 2°ETAPA: A CTA. CUOTA 9 | E61: 121000 | F61: {=E61/G61} -> 3270.2703 | G61: 37
A62: 43452 | C62: NES S.A. | D62: 2ºETAPA: CUOTA Nº9 (SALDO) | E62: 68714 | F62: 1808 | G62: 36.5
A63: 43468 | C63: NES S.A. | D63: 2º ETAPA: CUOTA 10 | E63: 168714 | F63: 4325.9028 | G63: 39.000876
A64: 43510 | C64: NES S.A. | D64: 2º ETAPA: CUOTA Nº11 | E64: 178836.84 | F64: 4706 | G64: 38.001878
A65: 43538 | C65: NES S.A. | D65: 2º ETAPA: CUOTA Nº12 | E65: 178836.84 | F65: 4238 | G65: 42.2
B67: TOTAL | E67: {=SUM(E46:E65)} -> 4824976.7 | F67: {=SUM(F46:F65)} -> 208655.32
C70: NES S.A.: JUAN 3°ETAPA: TRABAJOS DE MAMPOSTERÍA
A72: FECHA | B72: COMPROBANTE | C72: PROVEEDOR | D72: CONCEPTO | E72: PESOS | F72: DOLARES | G72: TIPO DE CAMBIO
A73: 20/09/2019 | B73: 589 | C73: NES S.A. | D73: TRABAJOS DE MAMPOSTERIA - CUOTA Nº 1 | E73: 247875.57 | F73: 3935 | G73: 63
A74: 20/09/2019 | C74: NES S.A. | D74: TRABAJO DE MAMPOSTERIA - ANTICIPO | E74: 1000000 | F74: 16700 | G74: 60
A75: 20/09/2019 | C75: NES S.A. | D75: TRABAJO DE MAMPOSTERIA - CUOTA Nº 1 | E75: 140168.34 | F75: 2337 | G75: 60
A76: 18/10/2019 | B76: 594 | C76: NES S.A. | D76: TRABAJOS DE MAMPOSTERIA - CUOTA Nº 2 | E76: 267209.87 | F76: 4110 | G76: 65
A77: 29/10/2019 | C77: NES S.A. | D77: TRABAJO DE MAMPOSTERIA - CUOTA Nº 2 | E77: 151101 | F77: 2159 | G77: 70
A78: 43773 | B78: 597 | C78: NES S.A. | D78: TRABAJOS DE MAMPOSTERIA - CUOTA Nº 3 | E78: 283242.45 | F78: 4360 | G78: 65
A79: 43780 | C79: NES S.A. | D79: TRABAJO MAMPOSTERIA - CUOTA Nº 3 | E79: 160167.56 | F79: 2465 | G79: 65
A80: 43597 | B80: 604 | C80: NES S.A. | D80: TRABAJOS DE MAMPOSTERIA - CUOTA Nº 4 | E80: 283242.45 | F80: 4165 | G80: {=E80/F80} -> 68.00539
A81: 18/12/2019 | C81: NES S.A. | D81: TRABAJO MAMPOSTERIA - CUOTA Nº 4 | E81: 160167.56 | F81: 2136 | G81: {=E81/F81} -> 74.984813
A82: 44013 | C82: NES S.A. | D82: TRABAJOS DE MAMPOSTERIA - CUOTA Nº 5 | E82: 300548.57 | F82: {=E82/G82} -> 4007.3143 | G82: 75
A83: 16/1/2020 | C83: NES S.A. | D83: TRABAJO MAMPOSTERIA - CUOTA Nº 5 | E83: 169950 | F83: 2266 | G83: {=E83/F83} -> 75
A84: 43984 | B84: 614 | C84: NES S.A. | D84: TRABAJOS DE MAMPOSTERIA - CUOTA Nº6 | E84: 312570.52 | F84: 4007 | G84: {=E84/F84} -> 78.006119
A85: 44106 | C85: NES S.A. | D85: TRABAJO MAMPOSTERIA - CUOTA Nº 6 | E85: 200751.95 | F85: 2509 | G85: {=E85/F85} -> 80.012734
A86: 43893 | C86: NES S.A. | D86: TRABAJO MAMPOSTERIA - CUOTA Nº 7 | E86: 212751.95 | F86: 2728 | G86: {=E86/F86} -> 77.988251
A87: 44107 | C87: NES S.A. | D87: TRABAJOS DE MAMPOSTERIA - CUOTA Nº7 | E87: 312570.52 | F87: {=E87/G87} -> 4007 | G87: {=G84} -> 78.006119
A88: 13/4 | B88: 626 | C88: NES S.A. | D88: TRABAJOS DE MAMPOSTERIA - CUOTA Nº8 | E88: 312570.52 | F88: 3722 | G88: {=E88/F88} -> 83.979183
A89: 14/4/2020 | C89: NES S.A. | D89: TRABAJO MAMPOSTERIA - CUOTA Nº 8 | E89: 212751.25 | F89: 2534 | G89: {=E89/F89} -> 83.958662
A90: 43956 | B90: 627 | C90: NES S.A. | D90: TRABAJOS DE MAMPOSTERIA - CUOTA Nº9 | E90: 312570.52 | F90: 2604 | G90: {=E90/F90} -> 120.03476
A91: 44170 | C91: NES S.A. | D91: TRABAJO MAMPOSTERIA - CUOTA Nº 9 | E91: 212751.75 | F91: 1743 | G91: {=E91/F91} -> 122.06067
A92: 44049 | C92: NES S.A. | D92: TRABAJO MAMPOSTERIA - CUOTA Nº 10 | E92: 471074.69 | F92: 3860 | G92: {=E92/F92} -> 122.04008
A93: 44050 | C93: NES S.A. | D93: TRABAJO MAMPOSTERIA - CUOTA Nº 11 | E93: 471074.69 | F93: 3770 | G93: {=E93/F93} -> 124.9535
A94: 44020 | C94: NES S.A. | D94: TRABAJOS MAMPOSTERÍA CUOTA N°12 | E94: 471074.69 | F94: 3490 | G94: {=E94/F94} -> 134.97842
A95: 43899 | C95: NES S.A. | D95: TRABAJOS MAMPOSTERÍA - CUOTA N°13 | E95: 471074.69 | F95: 3515 | G95: {=E95/F95} -> 134.0184
A96: 43992 | C96: NES S.A. | D96: TRABAJOS MAMPOSTERÍA - CUOTA N°14 | E96: 471074.69 | F96: 3140 | G96: {=E96/F96} -> 150.02379
A97: 44085 | C97: NES S.A. | D97: TRABAJOS MAMPOSTERÍA - CUOTA N°15 | E97: 471074 | F97: 3150 | G97: {=E97/F97} -> 149.5473
A98: 30/11/2020 | C98: NES S.A. | D98: TRABAJOS MAMPOSTERÍA - CUOTA N°16 | E98: 543800 | F98: 3441 | G98: {=E98/F98} -> 158.03545
C100: TOTAL | E100: {=SUM(E73:E98)} -> 8623209.8 | F100: {=SUM(F73:F98)} -> 96860.314

Sheet ELECTRICIDAD
A1: FECHA | B1: COMPROBANTE | C1: PROVEEDOR | D1: CONCEPTO | E1: PESOS | F1: DOLARES | G1: TIPO DE CAMBIO
A2: 42618 | C2: DIEGO - M.O. | D2: LOZAS | E2: 54000 | F2: 3220 | G2: {=E2/F2} -> 16.770186
A3: 42663 | C3: CASA BLANCO | D3: MATERIALES | E3: 60000 | F3: 3636 | G3: {=E3/F3} -> 16.50165
A4: 42928 | C4: CASA BLANCO | D4: MATERIALES | E4: 1200 | F4: 70 | G4: {=E4/F4} -> 17.142857
A5: 43062 | C5: CIARDI HNOS. | D5: COMPRA | E5: 3756.76 | F5: {=E5/G5} -> 227.65966 | G5: {=G3} -> 16.50165
A6: 43119 | C6: CIARDI HNOS. | D6: COMPRA | E6: 20397.96 | F6: 1046 | G6: {=E6/F6} -> 19.500918
A7: 43273 | C7: CASA BLANCO | D7: MANGUERAS - CAJAS | E7: 464872.5 | F7: 17500 | G7: 28
A8: 43312 | C8: DIEGO - M.O. | D8: A CTA. | E8: 31000 | F8: 1100 | G8: 27.8
A9: 43343 | C9: DIEGO - M.O. | D9: A CTA. | E9: 40000 | F9: {=E9/G9} -> 1081.0811 | G9: 37
A10: 43343 | B10: 11368 | C10: MACROFER | D10: FERRETERIA PARA ELECTRICIDAD | E10: 9606.88 | F10: 246 | G10: {=E10/F10} -> 39.052358
A11: 43426 | B11: 9635 | C11: ELECTRICIDAD | D11: CASA BLANCO - MATERIALES VARIOS | E11: 21985.82 | F11: 605 | G11: {=E11/F11} -> 36.340198
B17: TOTAL | E17: {=SUM(E2:E16)} -> 706819.92 | F17: {=SUM(F2:F16)} -> 28731.741

Sheet PLOMERIA
A1: FECHA | B1: COMPROBANTE | C1: PROVEEDOR | D1: CONCEPTO | E1: PESOS | F1: DOLARES | G1: TIPO DE CAMBIO
A2: 43123 | C2: SANITARIOS SANCHEZ | D2: DESAGUES | E2: 21450 | F2: 1100 | G2: {=E2/F2} -> 19.5
A3: 43149 | C3: TOLOZA - M.O. | D3: DESAGUES | E3: 38000 | F3: 1800 | G3: {=E3/F3} -> 21.111111
A4: 43231 | C4: PLOMERIA | D4: DESAGUES | E4: 3668 | F4: 158 | G4: {=E4/F4} -> 23.21519
A5: 43270 | C5: PLOMERIA | D5: TRABAJO DE CAÑERIAS EN PILETAS | E5: 20000 | F5: {=E5/G5} -> 714.28571 | G5: 28
A6: 43336 | B6: 147 | C6: GARRIDO | D6: ENTRADA DE AGUA | E6: 3000 | F6: 90 | G6: {=E6/F6} -> 33.333333
B9: TOTAL | E9: {=SUM(E3:E7)} -> 64668 | F9: {=SUM(F3:F7)} -> 2762.2857

Sheet ARQUITECTO
A1: FECHA | B1: COMPROBANTE | C1: PROVEEDOR | D1: CONCEPTO | E1: PESOS | F1: DOLARES | G1: TIPO DE CAMBIO
A2: JUL - 2013 | C2: ARQUITECTO AGUERO MERCENARO | D2: HONORARIOS | E2: 35000 | F2: 5000 | G2: 7 | I2: 5000
A3: AGOS - 2013 | C3: ARQUITECTO AGUERO MERCENARO | D3: HONORARIOS | E3: 36000 | F3: 5000 | G3: 7 | I3: 5000
A4: SEP - 2013 | C4: ARQUITECTO AGUERO MERCENARO | D4: HONORARIOS | E4: 220000 | F4: 30000 | G4: 7.33 | I4: 30000
A5: 41845 | C5: ARQUITECTO AGUERO MERCENARO | D5: HONORARIOS | E5: 150000 | F5: 15000 | G5: 10 | I5: 12397
A6: 42417 | C6: ARQUITECTO AGUERO MERCENARO | D6: HONORARIOS | E6: 200000 | F6: 15000 | G6: 13.3 | I6: 15000
A7: 42584 | C7: ARQUITECTO AGUERO MERCENARO | D7: CUOTA 01 - AÑO 2016 | E7: 148000 | F7: 10000 | G7: {=E7/F7} -> 14.8 | I7: 10000
A8: 42789 | C8: ARQUITECTO AGUERO MERCENARO | D8: CUOTA 02 - AÑO 2017 | E8: 160000 | F8: 10000 | G8: 16 | I8: 10000
A9: 43088 | C9: ARQUITECTO AGUERO MERCENARO | D9: CUOTA 3 - AÑO 2018 | E9: 200000 | F9: 10000 | G9: 20 | H9: 50% Y 50% | I9: {=4132+5000} -> 9132
I12: {=SUM(I2:I9)} -> 96529
B13: TOTAL | E13: {=SUM(E2:E12)} -> 1149000 | F13: {=SUM(F2:F12)} -> 100000

Sheet DRAP
A1: FECHA | B1: COMPROBANTE | C1: PROVEEDOR | D1: CONCEPTO | E1: PESOS | F1: DOLARES | G1: TIPO DE CAMBIO
A2: 42936 | C2: PINTURAS - DRAP | D2: PROTEX | E2: 1889.4 | F2: 111 | G2: {=E2/F2} -> 17.021622
A3: 42985 | B3: 56134/64020 NC 4565 | C3: PINTURAS - DRAP | D3: COMPRA | E3: {=16596.2-3319.24} -> 13276.96 | F3: 920 | G3: {=E3/F3} -> 14.431478
A4: 43028 | B4: 56866/57357/57245 | C4: PINTURAS - DRAP | D4: COMPRA | E4: 9158.43 | F4: 602 | G4: 18
A5: 43037 | C5: PINTURAS - DRAP | D5: COMPRA | E5: 13130 | F5: 744 | G5: {=E5/F5} -> 17.647849
A6: 43055 | C6: PINTURAS - DRAP | D6: COMPRA | E6: 11724.33 | F6: 660 | G6: {=E6/F6} -> 17.764136
A7: DIC -2017 | B7: 55425 | C7: PINTURAS - DRAP | D7: COMPRA | E7: 22078 | F7: 1300 | G7: {=E7/F7} -> 16.983077
A8: 43082 | C8: PINTURAS - DRAP | D8: COMPRA | E8: 8680 | F8: 500 | G8: 17.36
A9: 43082 | C9: PINTURAS - DRAP | D9: COMPRA | E9: 1224 | F9: 90 | G9: {=G8} -> 17.36
A10: 43092 | C10: PINTURAS - DRAP | D10: COMPRA | E10: 3243.05 | F10: {=E10/G10} -> 175.3 | G10: 18.5
A11: 43096 | C11: PINTURAS - DRAP | D11: TACURU | E11: 1880.83 | F11: {=E11/G11} -> 98.991053 | G11: 19
A12: 43125 | C12: PINTURAS - DRAP | D12: COMPRA | E12: 5545.08 | F12: {=E12/G12} -> 277.254 | G12: 20
A13: 43196 | C13: PINTURAS - DRAP | D13: MALLA DE FIBRA | E13: 2434.02 | F13: 118 | G13: {=E13/F13} -> 20.627288
A14: 43249 | C14: PINTURAS - DRAP | D14: COMPRA | E14: 7980 | F14: {=E14/G14} -> 310.50584 | G14: 25.7
A15: 43326 | C15: PINTURAS - DRAP | D15: PINTURA | E15: 3042.27 | F15: 101 | G15: {=E15/F15} -> 30.121485
A16: 43327 | C16: PINTURAS - DRAP | D16: PINTURA | E16: 3522.2 | F16: 117 | G16: {=E16/F16} -> 30.104274
A17: 43333 | B17: 838 | C17: PINTURAS - DRAP | D17: PINTURA VARIOS | E17: {=14126.78-2825.35} -> 11301.43 | F17: 353 | G17: {=E17/F17} -> 32.015382
A18: 43354 | B18: 63447 | C18: PINTURAS - DRAP | D18: LATEX, RODILLO, PINCEL, LIJAS, ETC | E18: 39020.73 | F18: 1012 | G18: {=E18/F18} -> 38.558034
A19: 43354 | B19: 63446 | C19: PINTURAS - DRAP | D19: ACOPIO - FIJADOR - MURO BLANCO | E19: 203712.03 | F19: 5290 | G19: {=E19/F19} -> 38.50889
A20: 43392 | B20: 64207 | C20: PINTURAS - DRAP | D20: FIJADOR, DURAMAX, CINTA, LIJA, ETC. | E20: 10592.78 | F20: {=E20/G20} -> 286.05941 | G20: 37.03
A21: 43403 | B21: 64423 | C21: PINTURAS - DRAP | D21: COLORANTE | E21: 2573.14 | F21: 70 | G21: {=E21/F21} -> 36.759143
A22: 43424 | B22: 64872 | C22: PINTURAS - DRAP | D22: MATERIALES VARIOS | E22: {=28894.68-86.12} -> 28808.56 | F22: 781 | G22: {=E22/F22} -> 36.886761
A23: 43413 | B23: 64643 | C23: PINTURAS - DRAP | D23: REVESTA | E23: 430.61 | F23: {=E23/G23} -> 11.829945 | G23: 36.4
B29: TOTAL | E29: {=SUM(E2:E28)} -> 405247.85 | F29: {=SUM(F2:F28)} -> 13928.94

Sheet ASCENSORES Y MONTA AUTOS
A1: FECHA | B1: COMPROBANTE | C1: PROVEEDOR | D1: CONCEPTO | E1: PESOS | F1: DOLARES | G1: TIPO DE CAMBIO
A2: 42913 | C2: ASCENSORES | D2: COMPRA MONTA AUTOS ULTRA | E2: 552500 | F2: 33500 | G2: {=E2/F2} -> 16.492537
A3: 42983 | C3: ASCENSORES | D3: IMPERM. HUECO ASCENSORES Y MONTA AUTOS | E3: 18000 | F3: 1000 | G3: 18
A4: 43042 | C4: ASCENSORES | D4: COMPRA MONTA AUTOS ULTRA | E4: 200000 | F4: 11100 | G4: {=E4/F4} -> 18.018018
A5: 43303 | C5: ASCENSORES | D5: 2 ASENSORES ( A CTA, SALDO EN FEB 2019) | E5: 1400000 | F5: 50000 | G5: {=E5/F5} -> 28
A6: 43343 | B6: 2199 | C6: ASCENSORES | D6: FACTURA JULIO | E6: 89460 | F6: {=E6/G6} -> 2417.8378 | G6: 37
A7: 43343 | B7: 2222 | C7: ASCENSORES | D7: FACTURA AGOSTO | E7: 59640 | F7: {=E7/G7} -> 1611.8919 | G7: {=G6} -> 37
A8: 43432 | B8: 2145 | C8: ASCENSORES | D8: PROYECTO Y DIRECCION INSTALACION MONTACOCHE | E8: 4700 | F8: {=E8/G8} -> 123.68421 | G8: 38
A9: 43501 | C9: ASCENSORES | D9: COMPRA MONTA AUTOS ULTRA(2017) SALDO | E9: 100000 | F9: 2632 | G9: 38
A10: 43501 | C10: ASCENSORES | D10: 2 ASENSORES ( A CTA DEL SALDO FEB 2019) | E10: 500000 | F10: 13160 | G10: {=E10/F10} -> 37.993921
A11: 43517 | C11: ASCENSORES | D11: 2 ASENSORES ( A CTA DEL SALDO FEB 2019) | E11: 500000 | F11: 12500 | G11: {=E11/F11} -> 40
B16: TOTAL | E16: {=SUM(E2:E14)} -> 3424300 | F16: {=SUM(F2:F14)} -> 128045.41

Sheet IMEPHO
A1: FECHA | B1: COMPROBANTE | C1: PROVEEDOR | D1: CONCEPTO | E1: PESOS | F1: DOLARES | G1: TIPO DE CAMBIO
A2: 41914 | B2: FACTURA 43425 | C2: IMEPHO | D2: HORMIGON - 392 M3 | E2: 449467.2 | F2: 32600 | G2: 13.8
A3: 41921 | B3: FACTURA 44179 | C3: IMEPHO | D3: HIERROS DE 12,16,20 Y 25 MM. | E3: 322719.6 | F3: 23730 | G3: 13.6
A4: 41947 | C4: IMEPHO | D4: HORMIGON - 392.5 M3 | E4: 450040.5 | F4: 32600 | G4: 13.8
A5: 42241 | B5: FACTURA 49634 | C5: IMEPHO | D5: COMPRA HORMIGON | E5: 599821.21 | F5: 37800 | G5: 15.87
A6: 42279 | C6: IMEPHO | D6: ACOPIO | E6: 1623051.8 | F6: 102078 | G6: 15.9
A7: 43173 | B7: FACTURA 69770 | C7: IMEPHO | D7: ACOPIO | E7: 666325 | F7: 32503 | G7: {=E7/F7} -> 20.500415
A8: 43187 | B8: FACTURA 4573 | C8: IMEPHO | D8: CERAMICO BAJO PILETA 100 M. | E8: 19374.43 | F8: 946 | G8: {=E8/F8} -> 20.48037
B10: TOTAL | E10: {=SUM(E2:E8)} -> 4130799.7 | F10: {=SUM(F2:F8)} -> 262257
